wordtree/__init__.py
wordtree-0.1.0.dist-info/METADATA
wordtree-0.1.0.dist-info/WHEEL
wordtree-0.1.0.dist-info/top_level.txt
wordtree-0.1.0.dist-info/RECORD
