Metadata-Version: 2.1
Name: wordtree
Version: 0.1.0
Summary: UNKNOWN
Home-page: UNKNOWN
Author: Will Crichton
Author-email: wcrichto@cs.stanford.edu
License: Apache 2.0
Platform: UNKNOWN
Requires-Dist: graphviz
Requires-Dist: pandas
Requires-Dist: tqdm
